setup.py
local_selenium_pool/__init__.py
local_selenium_pool/decorator.py
local_selenium_pool/output_parser.py
local_selenium_pool/output_queue.py
local_selenium_pool/pool.py
local_selenium_pool/selenium_worker.py
local_selenium_pool/test_case.py
local_selenium_pool.egg-info/PKG-INFO
local_selenium_pool.egg-info/SOURCES.txt
local_selenium_pool.egg-info/dependency_links.txt
local_selenium_pool.egg-info/not-zip-safe
local_selenium_pool.egg-info/requires.txt
local_selenium_pool.egg-info/top_level.txt